vpip/__init__.py
vpip/__main__.py
vpip/cli.py
vpip/dependency.py
vpip/execute.py
vpip/linker.py
vpip/pip_api.py
vpip/pypi.py
vpip/run_as_admin.py
vpip/venv.py
vpip/commands/__init__.py
vpip/commands/install.py
vpip/commands/link.py
vpip/commands/list.py
vpip/commands/outdated.py
vpip/commands/run.py
vpip/commands/uninstall.py
vpip/commands/update.py
vpip/commands/update_venv.py
vpip-0.11.1.dist-info/licenses/LICENSE
vpip-0.11.1.dist-info/METADATA
vpip-0.11.1.dist-info/WHEEL
vpip-0.11.1.dist-info/entry_points.txt
vpip-0.11.1.dist-info/top_level.txt
vpip-0.11.1.dist-info/RECORD
