Metadata-Version: 2.4
Name: vpip
Version: 0.11.1
Summary: A CLI which aims to provide an npm-like experience when working with Python packages.
Author-email: eight <eight04@gmail.com>
License: MIT
Project-URL: Homepage, https://github.com/eight04/vpip
Keywords: pip,pipm,pipx,venv,vex,virtualenv,pipenv,pdm,poetry
Classifier: Development Status :: 4 - Beta
Classifier: Environment :: Console
Classifier: Environment :: Win32 (MS Windows)
Classifier: Intended Audience :: Developers
Classifier: License :: OSI Approved :: MIT License
Classifier: Natural Language :: Chinese (Traditional)
Classifier: Operating System :: Microsoft :: Windows :: Windows 7
Classifier: Programming Language :: Python :: 3.10
Classifier: Programming Language :: Python :: 3.11
Classifier: Programming Language :: Python :: 3.12
Classifier: Programming Language :: Python :: 3.13
Classifier: Topic :: Software Development :: Build Tools
License-File: LICENSE
Requires-Dist: case-conversion~=2.1
Requires-Dist: configupdater~=3.2
Requires-Dist: namedpipe~=0.3.0
Requires-Dist: packaging~=25.0
Requires-Dist: requests~=2.32
Requires-Dist: tomlkit~=0.13.3
Dynamic: license-file
